setup.py
bagent/__init__.py
bagent/core.py
bagent/messages.py
bagent.egg-info/PKG-INFO
bagent.egg-info/SOURCES.txt
bagent.egg-info/dependency_links.txt
bagent.egg-info/entry_points.txt
bagent.egg-info/top_level.txt