Metadata-Version: 1.1
Name: bagent
Version: 0.5.1
Summary: Minimal & Simple Agent Engine for Python
Home-page: https://github.com/jepemo/basic-agent
Author: Jeremies Pérez Morata
Author-email: jeremiespm@gmail.com
License: MIT
Keywords: distributedsystems,concurrentprogramming,agents,aio,asyncio
Platform: UNKNOWN
Classifier: Development Status :: 5 - Production/Stable
Classifier: Intended Audience :: Developers
Classifier: License :: OSI Approved :: GNU General Public License v3 (GPLv3)
Classifier: Programming Language :: Python :: 3
Classifier: Programming Language :: Python :: 3.3
Classifier: Programming Language :: Python :: 3.4
Classifier: Programming Language :: Python :: 3.5
Classifier: Programming Language :: Python :: 3.6
Classifier: Topic :: Software Development
Classifier: Topic :: System :: Distributed Computing
